{
  "status": "success",
  "generated_at": "2025-11-24T20:02:07.557360+00:00",
  "added_terms": [],
  "conflicts": [
    {
      "record_id": "2",
      "excel_name": "jokes",
      "qb_name": "Inventory Asset",
      "excel_number": "50200",
      "qb_number": "12100",
      "excel_type": "hello",
      "qb_type": "OtherCurrentAsset",
      "reason": "data_mismatch"
    },
    {
      "record_id": "1",
      "excel_name": "Materials",
      "qb_name": "Accounts Receivable",
      "excel_number": "50101",
      "qb_number": "11000",
      "excel_type": "Cost of Goods Sold",
      "qb_type": "AccountsReceivable",
      "reason": "data_mismatch"
    },
    {
      "record_id": "0",
      "excel_name": null,
      "qb_name": "bank",
      "reason": "missing_in_excel"
    },
    {
      "record_id": "3",
      "excel_name": null,
      "qb_name": "Undeposited Funds",
      "reason": "missing_in_excel"
    },
    {
      "record_id": "4",
      "excel_name": null,
      "qb_name": "Accounts Payable",
      "reason": "missing_in_excel"
    },
    {
      "record_id": "5",
      "excel_name": null,
      "qb_name": "Payroll Liabilities",
      "reason": "missing_in_excel"
    },
    {
      "record_id": "6",
      "excel_name": null,
      "qb_name": "Opening Balance Equity",
      "reason": "missing_in_excel"
    },
    {
      "record_id": "20",
      "excel_name": null,
      "qb_name": "Members Equity",
      "reason": "missing_in_excel"
    },
    {
      "record_id": "21",
      "excel_name": null,
      "qb_name": "new",
      "reason": "missing_in_excel"
    },
    {
      "record_id": "7",
      "excel_name": null,
      "qb_name": "Sales",
      "reason": "missing_in_excel"
    },
    {
      "record_id": "8",
      "excel_name": null,
      "qb_name": "Cost of Goods Sold",
      "reason": "missing_in_excel"
    },
    {
      "record_id": "9",
      "excel_name": null,
      "qb_name": "Payroll Expenses",
      "reason": "missing_in_excel"
    },
    {
      "record_id": "101",
      "excel_name": null,
      "qb_name": "Test Account 101",
      "reason": "missing_in_excel"
    },
    {
      "record_id": "102",
      "excel_name": null,
      "qb_name": "Test Account 102",
      "reason": "missing_in_excel"
    },
    {
      "record_id": "123",
      "excel_name": null,
      "qb_name": "new purchase",
      "reason": "missing_in_excel"
    }
  ],
  "error": null
}